sqc/__init__.py
sqc/_query.py
sqc/_transpiler.py
sqc-0.1.0.dist-info/LICENSE
sqc-0.1.0.dist-info/WHEEL
sqc-0.1.0.dist-info/METADATA
sqc-0.1.0.dist-info/RECORD
