Metadata-Version: 2.1
Name: sqc
Version: 0.1.0
Summary: SQL queries to collections
Author: Anexen
Classifier: License :: OSI Approved :: MIT License
Classifier: Intended Audience :: Developers
Classifier: Topic :: Software Development :: Code Generators
Classifier: Programming Language :: SQL
Classifier: Programming Language :: Python :: 3
Requires-Dist: convtools
Requires-Dist: sqloxide
Requires-Dist: pytest ; extra == "test"
Requires-Dist: pytest-cov ; extra == "test"
Project-URL: Home, https://github.com/Anexen/sqc
Provides-Extra: test
